conforce/__init__.py
conforce/__version__.py
conforce/_cf_c.dll
conforce/_cf_c.so
conforce/cf_c.py
conforce/element_type_mapping.py
conforce/tensor_util.py
conforce_gen/__init__.py
conforce_gen/_codegen_c_header.c
conforce_gen/_codegen_python_header.py
conforce_gen/_element_integration_data.json
conforce_gen/codegen.py
conforce_gen/element_definitions.py
conforce_gen/expressions.py
conforce_gen/one_element_runner.py
conforce_gen/symbolic_util.py
conforce-1.0.5.dist-info/LICENSE.txt
conforce-1.0.5.dist-info/METADATA
conforce-1.0.5.dist-info/WHEEL
conforce-1.0.5.dist-info/top_level.txt
conforce-1.0.5.dist-info/RECORD
