Metadata-Version: 2.1
Name: conforce
Version: 1.0.5
Summary: Compute Configurational Forces using a fast C-Extension
Home-page: https://conforce.readthedocs.io/
Author: Matthias Rettl, Markus Tauscher, Sigfried Frankl, Martin Pletz
Author-email: matthias.rettl@unileoben.ac.at
Project-URL: Documentation, https://conforce.readthedocs.io/
Project-URL: Source, https://github.com/mrettl/conforce
Project-URL: Tracker, https://github.com/mrettl/conforce/issues
Classifier: Intended Audience :: Science/Research
Classifier: Operating System :: POSIX :: Linux
Classifier: Operating System :: Microsoft :: Windows
Classifier: Topic :: Scientific/Engineering :: Physics
Classifier: Topic :: Scientific/Engineering :: Mathematics
Classifier: License :: OSI Approved :: MIT License
Classifier: Programming Language :: Python :: 3 :: Only
Classifier: Development Status :: 5 - Production/Stable
Requires-Python: >=3.7
License-File: LICENSE.txt
Requires-Dist: numpy >=1.22
Requires-Dist: sympy >=1.10.1
Provides-Extra: doc
Requires-Dist: Sphinx >=5.0 ; extra == 'doc'
Requires-Dist: recommonmark >=0.7 ; extra == 'doc'
Requires-Dist: sphinx-rtd-theme ; extra == 'doc'
Provides-Extra: examples
Requires-Dist: matplotlib >=3.0 ; extra == 'examples'
